odfi_templates/__init__.py
odfi_templates/extensions/__init__.py
odfi_templates/extensions/code.py
odfi_templates/extensions/pdf.py
odfi_templates/extensions/questions.py
odfi_templates/extensions/scala.py
odfi_templates/extensions/stepsrecorder.py
odfi_templates/extensions/svg.py
odfi_templates/extensions/testext.py
odfi_templates/mariana/__init__.py
odfi_templates/mariana/breadcrumbs.html
odfi_templates/mariana/footer.html
odfi_templates/mariana/layout.html
odfi_templates/mariana/layout_old.html
odfi_templates/mariana/search.html
odfi_templates/mariana/searchbox.html
odfi_templates/mariana/theme.conf
odfi_templates/mariana/versions.html
odfi_templates/mariana/__pycache__/__init__.cpython-310.pyc
odfi_templates/mariana/static/css/badge_only.css
odfi_templates/mariana/static/css/badge_only.css.map
odfi_templates/mariana/static/css/mariana.css
odfi_templates/mariana/static/css/highlight-styles/a11y-dark.min.css
odfi_templates/mariana/static/css/highlight-styles/a11y-light.min.css
odfi_templates/mariana/static/css/highlight-styles/agate.min.css
odfi_templates/mariana/static/css/highlight-styles/an-old-hope.min.css
odfi_templates/mariana/static/css/highlight-styles/androidstudio.min.css
odfi_templates/mariana/static/css/highlight-styles/arduino-light.min.css
odfi_templates/mariana/static/css/highlight-styles/arta.min.css
odfi_templates/mariana/static/css/highlight-styles/ascetic.min.css
odfi_templates/mariana/static/css/highlight-styles/atom-one-dark-reasonable.min.css
odfi_templates/mariana/static/css/highlight-styles/atom-one-dark.min.css
odfi_templates/mariana/static/css/highlight-styles/atom-one-light.min.css
odfi_templates/mariana/static/css/highlight-styles/brown-paper.min.css
odfi_templates/mariana/static/css/highlight-styles/brown-papersq.png
odfi_templates/mariana/static/css/highlight-styles/codepen-embed.min.css
odfi_templates/mariana/static/css/highlight-styles/color-brewer.min.css
odfi_templates/mariana/static/css/highlight-styles/dark.min.css
odfi_templates-1.1.0.dist-info/METADATA
odfi_templates-1.1.0.dist-info/WHEEL
odfi_templates-1.1.0.dist-info/top_level.txt
odfi_templates-1.1.0.dist-info/RECORD
